launchpad/__init__.py
launchpad/dynamicapplication.py
launchpad/handlers.py
launchpad/main.py
launchpad/templates/error.html
launchpad/templates/loading.html
launchpad/templates/main.html
streamlit_launchpad-0.0.11.dist-info/LICENSE
streamlit_launchpad-0.0.11.dist-info/METADATA
streamlit_launchpad-0.0.11.dist-info/WHEEL
streamlit_launchpad-0.0.11.dist-info/entry_points.txt
streamlit_launchpad-0.0.11.dist-info/top_level.txt
streamlit_launchpad-0.0.11.dist-info/RECORD
