Metadata-Version: 2.1
Name: streamlit-launchpad
Version: 0.0.11
Summary: Web launchpad to browse a folder containing multiple Streamlit applications
Home-page: https://github.com/ideonate/streamlit-launchpad
Author: Dan Lester
Author-email: dan@ideonate.com
License: UNKNOWN
Platform: UNKNOWN
Classifier: Programming Language :: Python :: 3
Classifier: License :: OSI Approved :: MIT License
Classifier: Operating System :: OS Independent
Requires-Python: >=3.6
Requires-Dist: streamlit (>=0.62.0)
Requires-Dist: tornado (>=5.0)
Requires-Dist: Click (>=7.0)
